pymarktools/__init__.py
pymarktools/check_options.py
pymarktools/cli.py
pymarktools/global_state.py
pymarktools/commands/__init__.py
pymarktools/commands/check.py
pymarktools/commands/refactor.py
pymarktools/core/__init__.py
pymarktools/core/async_checker.py
pymarktools/core/gitignore.py
pymarktools/core/image_checker.py
pymarktools/core/link_checker.py
pymarktools/core/markdown.py
pymarktools/core/models.py
pymarktools/core/refactor.py
pymarktools-0.3.0.dist-info/METADATA
pymarktools-0.3.0.dist-info/WHEEL
pymarktools-0.3.0.dist-info/entry_points.txt
pymarktools-0.3.0.dist-info/licenses/LICENSE
pymarktools-0.3.0.dist-info/RECORD
