Metadata-Version: 2.4
Name: pymarktools
Version: 0.3.0
Summary: A set of markdown utilities for Python, designed to simplify the manipulation and parsing of markdown text. This project leverages Typer for a user-friendly command line interface and is built with a solid codebase structure to facilitate easy development and testing.
Project-URL: Homepage, https://github.com/jancschaefer/pymarktools
Project-URL: Documentation, https://github.com/jancschaefer/pymarktools/blob/main/README.md
Project-URL: Repository, https://github.com/jancschaefer/pymarktools
Project-URL: Issues, https://github.com/jancschaefer/pymarktools/issues
Project-URL: Changelog, https://github.com/jancschaefer/pymarktools/blob/main/CHANGELOG.md
Author-email: Jan Schäfer <jan@schae.fr>
License-Expression: MIT
License-File: LICENSE
Classifier: Development Status :: 4 - Beta
Classifier: Intended Audience :: Developers
Classifier: License :: OSI Approved :: MIT License
Classifier: Programming Language :: Python :: 3 :: Only
Classifier: Programming Language :: Python :: 3.13
Classifier: Programming Language :: Python :: Implementation :: CPython
Classifier: Topic :: Software Development :: Libraries
Classifier: Typing :: Typed
Requires-Python: >=3.12
Requires-Dist: gitignore-parser>=0.1.12
Requires-Dist: httpx>=0.28.1
Requires-Dist: typer>=0.16.0
